[
  {
    "name": "annual report on exchange arrangements and exchange restrictions 2023 opens in a new window.xml",
    "file_type": "other",
    "url": "https://www.elibrary.imf.org/display/book/9798400260391/9798400260391.xml"
  },
  {
    "name": "lk-com-dsp-imf.org",
    "file_type": "other",
    "url": "https://elibrary.imf.org/view/journals/002/2025/279/002.2025.issue-279-en.xml?cid=lk-com-dsp-imf.org"
  },
  {
    "name": "lk-com-dsp-imf.org",
    "file_type": "other",
    "url": "https://elibrary.imf.org/view/journals/002/2025/278/002.2025.issue-278-en.xml?cid=lk-com-dsp-imf.org"
  },
  {
    "name": "lk-com-dsp-imf.org",
    "file_type": "other",
    "url": "https://elibrary.imf.org/view/journals/001/2025/196/001.2025.issue-196-en.xml?cid=lk-com-dsp-imf.org"
  },
  {
    "name": "lk-com-dsp-imf.org",
    "file_type": "other",
    "url": "https://elibrary.imf.org/view/journals/007/2025/031/007.2025.issue-031-en.xml?cid=lk-com-dsp-imf.org"
  },
  {
    "name": "lk-com-dsp-imf.org",
    "file_type": "other",
    "url": "https://elibrary.imf.org/view/journals/061/2025/007/061.2025.issue-007-en.xml?cid=lk-com-dsp-imf.org"
  },
  {
    "name": "lk-com-dsp-imf.org",
    "file_type": "other",
    "url": "https://elibrary.imf.org/view/journals/001/2025/195/001.2025.issue-195-en.xml?cid=lk-com-dsp-imf.org"
  },
  {
    "name": "lk-com-dsp-imf.org",
    "file_type": "other",
    "url": "https://elibrary.imf.org/view/journals/001/2025/192/001.2025.issue-192-en.xml?cid=lk-com-dsp-imf.org"
  },
  {
    "name": "lk-com-dsp-imf.org",
    "file_type": "other",
    "url": "https://elibrary.imf.org/view/journals/001/2025/191/001.2025.issue-191-en.xml?cid=lk-com-dsp-imf.org"
  },
  {
    "name": "lk-com-dsp-imf.org",
    "file_type": "other",
    "url": "https://elibrary.imf.org/view/journals/001/2025/190/001.2025.issue-190-en.xml?cid=lk-com-dsp-imf.org"
  },
  {
    "name": "lk-com-dsp-imf.org",
    "file_type": "other",
    "url": "https://elibrary.imf.org/view/journals/001/2025/194/001.2025.issue-194-en.xml?cid=lk-com-dsp-imf.org"
  },
  {
    "name": "lk-com-dsp-imf.org",
    "file_type": "other",
    "url": "https://elibrary.imf.org/view/journals/001/2025/189/001.2025.issue-189-en.xml?cid=lk-com-dsp-imf.org"
  },
  {
    "name": "lk-com-dsp-imf.org",
    "file_type": "other",
    "url": "https://elibrary.imf.org/view/journals/018/2025/128/018.2025.issue-128-en.xml?cid=lk-com-dsp-imf.org"
  },
  {
    "name": "lk-com-dsp-imf.org",
    "file_type": "other",
    "url": "https://elibrary.imf.org/view/journals/018/2025/129/018.2025.issue-129-en.xml?cid=lk-com-dsp-imf.org"
  },
  {
    "name": "lk-com-dsp-imf.org",
    "file_type": "other",
    "url": "https://elibrary.imf.org/view/journals/006/2025/004/006.2025.issue-004-en.xml?cid=lk-com-dsp-imf.org"
  },
  {
    "name": "lk-com-dsp-imf.org",
    "file_type": "other",
    "url": "https://elibrary.imf.org/view/journals/002/2025/277/002.2025.issue-277-en.xml?cid=lk-com-dsp-imf.org"
  },
  {
    "name": "lk-com-dsp-imf.org",
    "file_type": "other",
    "url": "https://elibrary.imf.org/view/journals/018/2025/127/018.2025.issue-127-en.xml?cid=lk-com-dsp-imf.org"
  },
  {
    "name": "lk-com-dsp-imf.org",
    "file_type": "other",
    "url": "https://elibrary.imf.org/view/journals/018/2025/126/018.2025.issue-126-en.xml?cid=lk-com-dsp-imf.org"
  },
  {
    "name": "lk-com-dsp-imf.org",
    "file_type": "other",
    "url": "https://elibrary.imf.org/view/journals/065/2025/004/065.2025.issue-004-en.xml?cid=lk-com-dsp-imf.org"
  },
  {
    "name": "lk-com-dsp-imf.org",
    "file_type": "other",
    "url": "https://elibrary.imf.org/view/journals/001/2025/175/001.2025.issue-175-en.xml?cid=lk-com-dsp-imf.org"
  },
  {
    "name": "lk-com-dsp-imf.org",
    "file_type": "other",
    "url": "https://elibrary.imf.org/view/journals/002/2025/276/002.2025.issue-276-en.xml?cid=lk-com-dsp-imf.org"
  },
  {
    "name": "lk-com-dsp-imf.org",
    "file_type": "other",
    "url": "https://elibrary.imf.org/view/journals/002/2025/275/002.2025.issue-275-en.xml?cid=lk-com-dsp-imf.org"
  },
  {
    "name": "lk-com-dsp-imf.org",
    "file_type": "other",
    "url": "https://elibrary.imf.org/view/journals/001/2025/184/001.2025.issue-184-en.xml?cid=lk-com-dsp-imf.org"
  },
  {
    "name": "lk-com-dsp-imf.org",
    "file_type": "other",
    "url": "https://elibrary.imf.org/view/journals/001/2025/188/001.2025.issue-188-en.xml?cid=lk-com-dsp-imf.org"
  },
  {
    "name": "lk-com-dsp-imf.org",
    "file_type": "other",
    "url": "https://elibrary.imf.org/view/journals/002/2025/274/002.2025.issue-274-en.xml?cid=lk-com-dsp-imf.org"
  },
  {
    "name": "lk-com-dsp-imf.org",
    "file_type": "other",
    "url": "https://elibrary.imf.org/view/journals/002/2025/273/002.2025.issue-273-en.xml?cid=lk-com-dsp-imf.org"
  },
  {
    "name": "lk-com-dsp-imf.org",
    "file_type": "other",
    "url": "https://elibrary.imf.org/view/journals/001/2025/186/001.2025.issue-186-en.xml?cid=lk-com-dsp-imf.org"
  },
  {
    "name": "lk-com-dsp-imf.org",
    "file_type": "other",
    "url": "https://elibrary.imf.org/view/journals/001/2025/185/001.2025.issue-185-en.xml?cid=lk-com-dsp-imf.org"
  },
  {
    "name": "lk-com-dsp-imf.org",
    "file_type": "other",
    "url": "https://elibrary.imf.org/view/journals/002/2025/272/002.2025.issue-272-en.xml?cid=lk-com-dsp-imf.org"
  },
  {
    "name": "lk-com-dsp-imf.org",
    "file_type": "other",
    "url": "https://elibrary.imf.org/view/journals/001/2025/187/001.2025.issue-187-en.xml?cid=lk-com-dsp-imf.org"
  },
  {
    "name": "BROWSELINK",
    "file_type": "word",
    "url": "https://view.officeapps.live.com/op/view.aspx?src=https%3A%2F%2Fmcusercontent.com%2Fd62b8c1570b4b45285fbb8f4b%2Ffiles%2F92180a24-337a-893e-7087-046aae762e72%2FFinal_Edits_FDATA_Finance_2025_pre_budget_consultation.docx&wdOrigin=BROWSELINK"
  },
  {
    "name": "lk-com-dsp-imf.org",
    "file_type": "other",
    "url": "https://elibrary.imf.org/view/journals/002/2025/271/002.2025.issue-271-en.xml?cid=lk-com-dsp-imf.org"
  },
  {
    "name": "lk-com-dsp-imf.org",
    "file_type": "other",
    "url": "https://elibrary.imf.org/view/journals/002/2025/270/002.2025.issue-270-en.xml?cid=lk-com-dsp-imf.org"
  },
  {
    "name": "lk-com-dsp-imf.org",
    "file_type": "other",
    "url": "https://elibrary.imf.org/view/journals/002/2025/268/002.2025.issue-268-en.xml?cid=lk-com-dsp-imf.org"
  },
  {
    "name": "lk-com-dsp-imf.org",
    "file_type": "other",
    "url": "https://elibrary.imf.org/view/journals/002/2025/267/002.2025.issue-267-en.xml?cid=lk-com-dsp-imf.org"
  },
  {
    "name": "lk-com-dsp-imf.org",
    "file_type": "other",
    "url": "https://elibrary.imf.org/view/journals/002/2025/269/002.2025.issue-269-en.xml?cid=lk-com-dsp-imf.org"
  },
  {
    "name": "lk-com-dsp-imf.org",
    "file_type": "other",
    "url": "https://elibrary.imf.org/view/journals/019/2025/084/019.2025.issue-084-en.xml?cid=lk-com-dsp-imf.org"
  },
  {
    "name": "lk-com-dsp-imf.org",
    "file_type": "other",
    "url": "https://elibrary.imf.org/view/journals/002/2025/259/002.2025.issue-259-en.xml?cid=lk-com-dsp-imf.org"
  },
  {
    "name": "lk-com-dsp-imf.org",
    "file_type": "other",
    "url": "https://elibrary.imf.org/view/journals/087/2025/005/087.2025.issue-005-en.xml?cid=lk-com-dsp-imf.org"
  },
  {
    "name": "lk-com-dsp-imf.org",
    "file_type": "other",
    "url": "https://elibrary.imf.org/view/journals/002/2025/258/002.2025.issue-258-en.xml?cid=lk-com-dsp-imf.org"
  },
  {
    "name": "lk-com-dsp-imf.org",
    "file_type": "other",
    "url": "https://elibrary.imf.org/view/journals/018/2025/124/018.2025.issue-124-en.xml?cid=lk-com-dsp-imf.org"
  },
  {
    "name": "lk-com-dsp-imf.org",
    "file_type": "other",
    "url": "https://elibrary.imf.org/view/journals/018/2025/125/018.2025.issue-125-en.xml?cid=lk-com-dsp-imf.org"
  },
  {
    "name": "lk-com-dsp-imf.org",
    "file_type": "other",
    "url": "https://elibrary.imf.org/view/journals/002/2025/266/002.2025.issue-266-en.xml?cid=lk-com-dsp-imf.org"
  },
  {
    "name": "lk-com-dsp-imf.org",
    "file_type": "other",
    "url": "https://elibrary.imf.org/view/journals/002/2025/263/002.2025.issue-263-en.xml?cid=lk-com-dsp-imf.org"
  },
  {
    "name": "lk-com-dsp-imf.org",
    "file_type": "other",
    "url": "https://elibrary.imf.org/view/journals/002/2025/264/002.2025.issue-264-en.xml?cid=lk-com-dsp-imf.org"
  },
  {
    "name": "_ftn4",
    "file_type": "word",
    "url": "https://usc-word-edit.officeapps.live.com/we/wordeditorframe.aspx?ui=en-US&rs=en-US&wopisrc=https%3A%2F%2Fintlmonetaryfund-my.sharepoint.com%2Fpersonal%2Fssmithtohu_imf_org%2F_vti_bin%2Fwopi.ashx%2Ffiles%2Fc6d95069b2e74afa931a9af31af2e4a9&wdlor=c5C4B6786-7F9D-429A-A039-32C806F2F7BD&wdenableroaming=1&mscc=1&wdodb=1&hid=D4703563-0BB1-4BCC-9BA3-703AC5440B76.0&uih=sharepointcom&wdlcid=en-US&jsapi=1&jsapiver=v2&corrid=1f22d7a8-f860-b73a-94c7-c19b0f74ff1a&usid=1f22d7a8-f860-b73a-94c7-c19b0f74ff1a&newsession=1&sftc=1&uihit=docaspx&muv=1&ats=PairwiseBroker&cac=1&sams=1&mtf=1&sfp=1&sdp=1&hch=1&hwfh=1&dchat=1&sc=%7B%22pmo%22%3A%22https%3A%2F%2Fintlmonetaryfund-my.sharepoint.com%22%2C%22pmshare%22%3Atrue%7D&ctp=LeastProtected&rct=Normal&wdorigin=Outlook-Body.Sharing.DirectLink.Copy.LOF&wdhostclicktime=1756144689443&afdflight=63&csiro=1&instantedit=1&wopicomplete=1&wdredirectionreason=Unified_SingleFlush#_ftn4"
  },
  {
    "name": "_ftn3",
    "file_type": "word",
    "url": "https://usc-word-edit.officeapps.live.com/we/wordeditorframe.aspx?ui=en-US&rs=en-US&wopisrc=https%3A%2F%2Fintlmonetaryfund-my.sharepoint.com%2Fpersonal%2Fssmithtohu_imf_org%2F_vti_bin%2Fwopi.ashx%2Ffiles%2Fc6d95069b2e74afa931a9af31af2e4a9&wdlor=c5C4B6786-7F9D-429A-A039-32C806F2F7BD&wdenableroaming=1&mscc=1&wdodb=1&hid=D4703563-0BB1-4BCC-9BA3-703AC5440B76.0&uih=sharepointcom&wdlcid=en-US&jsapi=1&jsapiver=v2&corrid=1f22d7a8-f860-b73a-94c7-c19b0f74ff1a&usid=1f22d7a8-f860-b73a-94c7-c19b0f74ff1a&newsession=1&sftc=1&uihit=docaspx&muv=1&ats=PairwiseBroker&cac=1&sams=1&mtf=1&sfp=1&sdp=1&hch=1&hwfh=1&dchat=1&sc=%7B%22pmo%22%3A%22https%3A%2F%2Fintlmonetaryfund-my.sharepoint.com%22%2C%22pmshare%22%3Atrue%7D&ctp=LeastProtected&rct=Normal&wdorigin=Outlook-Body.Sharing.DirectLink.Copy.LOF&wdhostclicktime=1756144689443&afdflight=63&csiro=1&instantedit=1&wopicomplete=1&wdredirectionreason=Unified_SingleFlush#_ftn3"
  },
  {
    "name": "_ftnref1",
    "file_type": "word",
    "url": "https://usc-word-edit.officeapps.live.com/we/wordeditorframe.aspx?ui=en-US&rs=en-US&wopisrc=https%3A%2F%2Fintlmonetaryfund-my.sharepoint.com%2Fpersonal%2Fssmithtohu_imf_org%2F_vti_bin%2Fwopi.ashx%2Ffiles%2Fc6d95069b2e74afa931a9af31af2e4a9&wdlor=c5C4B6786-7F9D-429A-A039-32C806F2F7BD&wdenableroaming=1&mscc=1&wdodb=1&hid=D4703563-0BB1-4BCC-9BA3-703AC5440B76.0&uih=sharepointcom&wdlcid=en-US&jsapi=1&jsapiver=v2&corrid=1f22d7a8-f860-b73a-94c7-c19b0f74ff1a&usid=1f22d7a8-f860-b73a-94c7-c19b0f74ff1a&newsession=1&sftc=1&uihit=docaspx&muv=1&ats=PairwiseBroker&cac=1&sams=1&mtf=1&sfp=1&sdp=1&hch=1&hwfh=1&dchat=1&sc=%7B%22pmo%22%3A%22https%3A%2F%2Fintlmonetaryfund-my.sharepoint.com%22%2C%22pmshare%22%3Atrue%7D&ctp=LeastProtected&rct=Normal&wdorigin=Outlook-Body.Sharing.DirectLink.Copy.LOF&wdhostclicktime=1756144689443&afdflight=63&csiro=1&instantedit=1&wopicomplete=1&wdredirectionreason=Unified_SingleFlush#_ftnref1"
  },
  {
    "name": "_ftnref4",
    "file_type": "word",
    "url": "https://usc-word-edit.officeapps.live.com/we/wordeditorframe.aspx?ui=en-US&rs=en-US&wopisrc=https%3A%2F%2Fintlmonetaryfund-my.sharepoint.com%2Fpersonal%2Fssmithtohu_imf_org%2F_vti_bin%2Fwopi.ashx%2Ffiles%2Fc6d95069b2e74afa931a9af31af2e4a9&wdlor=c5C4B6786-7F9D-429A-A039-32C806F2F7BD&wdenableroaming=1&mscc=1&wdodb=1&hid=D4703563-0BB1-4BCC-9BA3-703AC5440B76.0&uih=sharepointcom&wdlcid=en-US&jsapi=1&jsapiver=v2&corrid=1f22d7a8-f860-b73a-94c7-c19b0f74ff1a&usid=1f22d7a8-f860-b73a-94c7-c19b0f74ff1a&newsession=1&sftc=1&uihit=docaspx&muv=1&ats=PairwiseBroker&cac=1&sams=1&mtf=1&sfp=1&sdp=1&hch=1&hwfh=1&dchat=1&sc=%7B%22pmo%22%3A%22https%3A%2F%2Fintlmonetaryfund-my.sharepoint.com%22%2C%22pmshare%22%3Atrue%7D&ctp=LeastProtected&rct=Normal&wdorigin=Outlook-Body.Sharing.DirectLink.Copy.LOF&wdhostclicktime=1756144689443&afdflight=63&csiro=1&instantedit=1&wopicomplete=1&wdredirectionreason=Unified_SingleFlush#_ftnref4"
  },
  {
    "name": "_ftnref2",
    "file_type": "word",
    "url": "https://usc-word-edit.officeapps.live.com/we/wordeditorframe.aspx?ui=en-US&rs=en-US&wopisrc=https%3A%2F%2Fintlmonetaryfund-my.sharepoint.com%2Fpersonal%2Fssmithtohu_imf_org%2F_vti_bin%2Fwopi.ashx%2Ffiles%2Fc6d95069b2e74afa931a9af31af2e4a9&wdlor=c5C4B6786-7F9D-429A-A039-32C806F2F7BD&wdenableroaming=1&mscc=1&wdodb=1&hid=D4703563-0BB1-4BCC-9BA3-703AC5440B76.0&uih=sharepointcom&wdlcid=en-US&jsapi=1&jsapiver=v2&corrid=1f22d7a8-f860-b73a-94c7-c19b0f74ff1a&usid=1f22d7a8-f860-b73a-94c7-c19b0f74ff1a&newsession=1&sftc=1&uihit=docaspx&muv=1&ats=PairwiseBroker&cac=1&sams=1&mtf=1&sfp=1&sdp=1&hch=1&hwfh=1&dchat=1&sc=%7B%22pmo%22%3A%22https%3A%2F%2Fintlmonetaryfund-my.sharepoint.com%22%2C%22pmshare%22%3Atrue%7D&ctp=LeastProtected&rct=Normal&wdorigin=Outlook-Body.Sharing.DirectLink.Copy.LOF&wdhostclicktime=1756144689443&afdflight=63&csiro=1&instantedit=1&wopicomplete=1&wdredirectionreason=Unified_SingleFlush#_ftnref2"
  },
  {
    "name": "_ftn2",
    "file_type": "word",
    "url": "https://usc-word-edit.officeapps.live.com/we/wordeditorframe.aspx?ui=en-US&rs=en-US&wopisrc=https%3A%2F%2Fintlmonetaryfund-my.sharepoint.com%2Fpersonal%2Fssmithtohu_imf_org%2F_vti_bin%2Fwopi.ashx%2Ffiles%2Fc6d95069b2e74afa931a9af31af2e4a9&wdlor=c5C4B6786-7F9D-429A-A039-32C806F2F7BD&wdenableroaming=1&mscc=1&wdodb=1&hid=D4703563-0BB1-4BCC-9BA3-703AC5440B76.0&uih=sharepointcom&wdlcid=en-US&jsapi=1&jsapiver=v2&corrid=1f22d7a8-f860-b73a-94c7-c19b0f74ff1a&usid=1f22d7a8-f860-b73a-94c7-c19b0f74ff1a&newsession=1&sftc=1&uihit=docaspx&muv=1&ats=PairwiseBroker&cac=1&sams=1&mtf=1&sfp=1&sdp=1&hch=1&hwfh=1&dchat=1&sc=%7B%22pmo%22%3A%22https%3A%2F%2Fintlmonetaryfund-my.sharepoint.com%22%2C%22pmshare%22%3Atrue%7D&ctp=LeastProtected&rct=Normal&wdorigin=Outlook-Body.Sharing.DirectLink.Copy.LOF&wdhostclicktime=1756144689443&afdflight=63&csiro=1&instantedit=1&wopicomplete=1&wdredirectionreason=Unified_SingleFlush#_ftn2"
  },
  {
    "name": "_ftn1",
    "file_type": "word",
    "url": "https://usc-word-edit.officeapps.live.com/we/wordeditorframe.aspx?ui=en-US&rs=en-US&wopisrc=https%3A%2F%2Fintlmonetaryfund-my.sharepoint.com%2Fpersonal%2Fssmithtohu_imf_org%2F_vti_bin%2Fwopi.ashx%2Ffiles%2Fc6d95069b2e74afa931a9af31af2e4a9&wdlor=c5C4B6786-7F9D-429A-A039-32C806F2F7BD&wdenableroaming=1&mscc=1&wdodb=1&hid=D4703563-0BB1-4BCC-9BA3-703AC5440B76.0&uih=sharepointcom&wdlcid=en-US&jsapi=1&jsapiver=v2&corrid=1f22d7a8-f860-b73a-94c7-c19b0f74ff1a&usid=1f22d7a8-f860-b73a-94c7-c19b0f74ff1a&newsession=1&sftc=1&uihit=docaspx&muv=1&ats=PairwiseBroker&cac=1&sams=1&mtf=1&sfp=1&sdp=1&hch=1&hwfh=1&dchat=1&sc=%7B%22pmo%22%3A%22https%3A%2F%2Fintlmonetaryfund-my.sharepoint.com%22%2C%22pmshare%22%3Atrue%7D&ctp=LeastProtected&rct=Normal&wdorigin=Outlook-Body.Sharing.DirectLink.Copy.LOF&wdhostclicktime=1756144689443&afdflight=63&csiro=1&instantedit=1&wopicomplete=1&wdredirectionreason=Unified_SingleFlush#_ftn1"
  },
  {
    "name": "_ftnref3",
    "file_type": "word",
    "url": "https://usc-word-edit.officeapps.live.com/we/wordeditorframe.aspx?ui=en-US&rs=en-US&wopisrc=https%3A%2F%2Fintlmonetaryfund-my.sharepoint.com%2Fpersonal%2Fssmithtohu_imf_org%2F_vti_bin%2Fwopi.ashx%2Ffiles%2Fc6d95069b2e74afa931a9af31af2e4a9&wdlor=c5C4B6786-7F9D-429A-A039-32C806F2F7BD&wdenableroaming=1&mscc=1&wdodb=1&hid=D4703563-0BB1-4BCC-9BA3-703AC5440B76.0&uih=sharepointcom&wdlcid=en-US&jsapi=1&jsapiver=v2&corrid=1f22d7a8-f860-b73a-94c7-c19b0f74ff1a&usid=1f22d7a8-f860-b73a-94c7-c19b0f74ff1a&newsession=1&sftc=1&uihit=docaspx&muv=1&ats=PairwiseBroker&cac=1&sams=1&mtf=1&sfp=1&sdp=1&hch=1&hwfh=1&dchat=1&sc=%7B%22pmo%22%3A%22https%3A%2F%2Fintlmonetaryfund-my.sharepoint.com%22%2C%22pmshare%22%3Atrue%7D&ctp=LeastProtected&rct=Normal&wdorigin=Outlook-Body.Sharing.DirectLink.Copy.LOF&wdhostclicktime=1756144689443&afdflight=63&csiro=1&instantedit=1&wopicomplete=1&wdredirectionreason=Unified_SingleFlush#_ftnref3"
  },
  {
    "name": "QFR_2021-sd-2019-12-31-ed-2025-06-30.json",
    "file_type": "other",
    "url": "https://www.bankofcanada.ca/valet/observations/group/QFR_2021/json?start_date=2019-12-31&end_date=2025-06-30"
  },
  {
    "name": "QFR_2021-sd-2019-12-31-ed-2025-06-30.xml",
    "file_type": "other",
    "url": "https://www.bankofcanada.ca/valet/observations/group/QFR_2021/xml?start_date=2019-12-31&end_date=2025-06-30"
  },
  {
    "name": "en_app_stat_II_trim_2025.zip",
    "file_type": "other",
    "url": "https://www.bancaditalia.it/pubblicazioni/sondaggio-abitazioni/2025-sondaggio-abitazioni/02/en_app_stat_II_trim_2025.zip"
  },
  {
    "name": "MPR_2025M07.xml",
    "file_type": "other",
    "url": "https://www.bankofcanada.ca/valet/observations/group/MPR_2025M07/xml"
  },
  {
    "name": "MPR_2025M07.json",
    "file_type": "other",
    "url": "https://www.bankofcanada.ca/valet/observations/group/MPR_2025M07/json"
  },
  {
    "name": "BOS_2025Q2-sd-1999-01-01-ed-2025-06-30.json",
    "file_type": "other",
    "url": "https://www.bankofcanada.ca/valet/observations/group/BOS_2025Q2/json?start_date=1999-01-01&end_date=2025-06-30"
  },
  {
    "name": "BOS_2025Q2-sd-1999-01-01-ed-2025-06-30.xml",
    "file_type": "other",
    "url": "https://www.bankofcanada.ca/valet/observations/group/BOS_2025Q2/xml?start_date=1999-01-01&end_date=2025-06-30"
  },
  {
    "name": "CSCE_2025Q2-sd-1999-01-01-ed-2025-06-30.xml",
    "file_type": "other",
    "url": "https://www.bankofcanada.ca/valet/observations/group/CSCE_2025Q2/xml?start_date=1999-01-01&end_date=2025-06-30"
  },
  {
    "name": "CSCE_2025Q2-sd-1999-01-01-ed-2025-06-30.json",
    "file_type": "other",
    "url": "https://www.bankofcanada.ca/valet/observations/group/CSCE_2025Q2/json?start_date=1999-01-01&end_date=2025-06-30"
  },
  {
    "name": "SAN_THOR20250611.xml",
    "file_type": "other",
    "url": "https://www.bankofcanada.ca/valet/observations/group/SAN_THOR20250611/xml"
  },
  {
    "name": "SAN_THOR20250611.json",
    "file_type": "other",
    "url": "https://www.bankofcanada.ca/valet/observations/group/SAN_THOR20250611/json"
  },
  {
    "name": "BE-3-2025-dati.zip",
    "file_type": "other",
    "url": "https://www.bancaditalia.it/pubblicazioni/bollettino-economico/2025-3/BE-3-2025-dati.zip"
  },
  {
    "name": "dati_2025_06_eng.zip",
    "file_type": "other",
    "url": "https://www.bancaditalia.it/pubblicazioni/indagine-inflazione/2025-indagine-inflazione/06/dati_2025_06_eng.zip"
  },
  {
    "name": "dati_2024_eng.zip",
    "file_type": "other",
    "url": "https://www.bancaditalia.it/pubblicazioni/indagine-imprese/2024-indagini-imprese/dati_2024_eng.zip"
  },
  {
    "name": "questionnaire_eng.zip",
    "file_type": "other",
    "url": "https://www.bancaditalia.it/pubblicazioni/indagine-imprese/2024-indagini-imprese/questionnaire_eng.zip"
  },
  {
    "name": "SAN_SUAD20250620.xml",
    "file_type": "other",
    "url": "https://www.bankofcanada.ca/valet/observations/group/SAN_SUAD20250620/xml"
  },
  {
    "name": "SAN_SUAD20250620.json",
    "file_type": "other",
    "url": "https://www.bankofcanada.ca/valet/observations/group/SAN_SUAD20250620/json"
  },
  {
    "name": "SAN_VALA20250605.xml",
    "file_type": "other",
    "url": "https://www.bankofcanada.ca/valet/observations/group/SAN_VALA20250605/xml"
  },
  {
    "name": "SAN_VALA20250605.json",
    "file_type": "other",
    "url": "https://www.bankofcanada.ca/valet/observations/group/SAN_VALA20250605/json"
  }
]